<annotation>
	<folder>dataset</folder>
	<filename>0-1-1-001593.jpg</filename>
	<path>C:\Users\23055\Desktop\dataset\0-1-1-001593.jpg</path>
	<source>
		<database>Unknown</database>
	</source>
	<size>
		<width>224</width>
		<height>224</height>
		<depth>3</depth>
	</size>
	<segmented>0</segmented>
	<object>
		<name>fire</name>
		<pose>Unspecified</pose>
		<truncated>0</truncated>
		<difficult>0</difficult>
		<bndbox>
			<xmin>80</xmin>
			<ymin>97</ymin>
			<xmax>107</xmax>
			<ymax>120</ymax>
		</bndbox>
	</object>
	<object>
		<name>smoke</name>
		<pose>Unspecified</pose>
		<truncated>0</truncated>
		<difficult>0</difficult>
		<bndbox>
			<xmin>84</xmin>
			<ymin>48</ymin>
			<xmax>186</xmax>
			<ymax>117</ymax>
		</bndbox>
	</object>
</annotation>
